{
  "municipality": "Op\u0107ina",
  "monitorNetwork": "Pratite svoju mre\u017eu digitalnih natpisa",
  "profile": "Profil",
  "logout": "Odjava",
  "loading": "U\u010ditavanje...",
  "dashboard": "Nadzorna plo\u010da",
  "totalDisplays": "Ukupno zaslona",
  "totalReports": "Ukupno izvje\u0161\u0107a",
  "activeContent": "Aktivan sadr\u017eaj",
  "totalUsers": "Ukupno korisnika",
  "recentActivity": "Nedavne aktivnosti",
  "noRecentActivity": "Nema prona\u0111enih nedavnih aktivnosti.",
  "report": "Izvje\u0161\u0107e",
  "statusPending": "na \u010dekaju",
  "statusInProgress": "u tijeku",
  "statusResolved": "rije\u0161eno",
  "statusRejected": "odbijeno",
  "displayStatus": "Status zaslona",
  "noDisplays": "Nema prona\u0111enih zaslona.",
  "uptime": "vrijeme rada",
  "views": "pregledi",
  "online": "online",
  "offline": "offline",
  "groupNotFound": "Grupa nije prona\u0111ena za trenutnog korisnika.",
  "failedLoadDashboard": "Neuspjelo u\u010ditavanje sa\u017eetka nadzorne plo\u010de.",
  "failedLoadToken": "Neuspjelo u\u010ditavanje tokena",
  "language": "Jezik"
}